{
    "unlockhash": "7c96369b69ad089196c39831ad86b51aa7921e6c0fe3e3293d1f5198b78337c6e43b5a5fff37",
    "siacoin_history": [
        {
            "income": {
                "value": "10145231195481332584330821632",
                "unlockhash": "7c96369b69ad089196c39831ad86b51aa7921e6c0fe3e3293d1f5198b78337c6e43b5a5fff37",
                "id": "72db03dd7dd65161dec1531004efc5f048c34d7feb8313a2f3bae5338372d3f1",
                "spent": {
                    "block": "000000000000003ffb1d5162460d2e5bdf64d30fb57d18aceca841d9f4e15065",
                    "blocki": 120064,
                    "tx": "25220589306e2c5bac43ab09807c2226518d2173bde9ec42141a8708512e5f24",
                    "index": 0,
                    "index0": null
                }
            },
            "income_source": {
                "block": "00000000000000335b5b185cf9a1143a8993d429106cc73dadefd1611b59e5f8",
                "blocki": 120062,
                "tx": "ec306e830440cce518d4ce1e2a63f84d69866e8b7eec860e4976b61c5946e42b",
                "index": 1,
                "nature": "siacoin_output",
                "index0": null
            },
            "income_tx": {
                "id": "ec306e830440cce518d4ce1e2a63f84d69866e8b7eec860e4976b61c5946e42b",
                "block": "00000000000000335b5b185cf9a1143a8993d429106cc73dadefd1611b59e5f8",
                "blocki": 120062,
                "size": 495,
                "siacoininputs": [
                    {
                        "parentid": "ff089e233574cb12ef712aaf26e0b9fae1a0829a55ec54716b334c57c0f6ed92",
                        "unlockconditions": {
                            "timelock": 0,
                            "publickeys": [
                                {
                                    "algorithm": "ed25519",
                                    "key": "zvRn7ZUXaL+9CEMW0IgvSHJ0Yw9ywMR9VAg1cfUKr2c="
                                }
                            ],
                            "signaturesrequired": 1
                        },
                        "parent": {
                            "value": "10145264435481332584330821632",
                            "unlockhash": "69c20b65849e5f060a572392d263e6c8bf1654514c36914e427fa7e70a6539118b3dae654d08"
                        },
                        "source": {
                            "block": "0000000000000006030b8f6a70531e72f4c7373d8649c90f41d4f4f5f5d32921",
                            "blocki": 120058,
                            "tx": "c7c6905ae231332661cb46136ccb91fcd6dbd4a4f2e799e0c909f38842885343",
                            "index": 1,
                            "nature": "siacoin_output",
                            "index0": null
                        }
                    }
                ],
                "siacoinoutputs": [
                    {
                        "value": "33240000000000000000000",
                        "unlockhash": "326995ff0579b10d3c066caf48b4b4e0609eced7238156833ecb8964f2a39a9952626e2c13e1",
                        "id": "666ec6f54e0979c515c0453b7a9468811a109a2e3b55a43feb4170c176dbe52d",
                        "spent": {
                            "block": "00000000000000335b5b185cf9a1143a8993d429106cc73dadefd1611b59e5f8",
                            "blocki": 120062,
                            "tx": "2be6441dd311684abe61406bb2ccc85cbb52160e1065aaf2431f5702d61b7e95",
                            "index": 0,
                            "index0": null
                        }
                    },
                    {
                        "value": "10145231195481332584330821632",
                        "unlockhash": "7c96369b69ad089196c39831ad86b51aa7921e6c0fe3e3293d1f5198b78337c6e43b5a5fff37",
                        "id": "72db03dd7dd65161dec1531004efc5f048c34d7feb8313a2f3bae5338372d3f1",
                        "spent": {
                            "block": "000000000000003ffb1d5162460d2e5bdf64d30fb57d18aceca841d9f4e15065",
                            "blocki": 120064,
                            "tx": "25220589306e2c5bac43ab09807c2226518d2173bde9ec42141a8708512e5f24",
                            "index": 0,
                            "index0": null
                        }
                    }
                ],
                "filecontracts": null,
                "filecontractrevisions": null,
                "storageproofs": null,
                "siafundinputs": null,
                "siafundoutputs": null,
                "minerfees": [],
                "arbitrarydata": [],
                "transactionsignatures": [
                    {
                        "parentid": "ff089e233574cb12ef712aaf26e0b9fae1a0829a55ec54716b334c57c0f6ed92",
                        "publickeyindex": 0,
                        "timelock": 0,
                        "coveredfields": {
                            "wholetransaction": true,
                            "siacoininputs": [],
                            "siacoinoutputs": [],
                            "filecontracts": [],
                            "filecontractrevisions": [],
                            "storageproofs": [],
                            "siafundinputs": [],
                            "siafundoutputs": [],
                            "minerfees": [],
                            "arbitrarydata": [],
                            "transactionsignatures": []
                        },
                        "signature": "Zh8lb/+CfjYUfFFrcnNNUjJeefJafZKfg+RUaYND9+2EyJZtzbH+LMN327KiIxNHAy7DVjbAFF8YYFilbhKJBA=="
                    }
                ]
            },
            "spent_tx": {
                "id": "25220589306e2c5bac43ab09807c2226518d2173bde9ec42141a8708512e5f24",
                "block": "000000000000003ffb1d5162460d2e5bdf64d30fb57d18aceca841d9f4e15065",
                "blocki": 120064,
                "size": 496,
                "siacoininputs": [
                    {
                        "parentid": "72db03dd7dd65161dec1531004efc5f048c34d7feb8313a2f3bae5338372d3f1",
                        "unlockconditions": {
                            "timelock": 0,
                            "publickeys": [
                                {
                                    "algorithm": "ed25519",
                                    "key": "c1Lw/PMgNOD1j0o//q+iUspeIYPVP6Fo2IRp9K8hrZE="
                                }
                            ],
                            "signaturesrequired": 1
                        },
                        "parent": {
                            "value": "10145231195481332584330821632",
                            "unlockhash": "7c96369b69ad089196c39831ad86b51aa7921e6c0fe3e3293d1f5198b78337c6e43b5a5fff37"
                        },
                        "source": {
                            "block": "00000000000000335b5b185cf9a1143a8993d429106cc73dadefd1611b59e5f8",
                            "blocki": 120062,
                            "tx": "ec306e830440cce518d4ce1e2a63f84d69866e8b7eec860e4976b61c5946e42b",
                            "index": 1,
                            "nature": "siacoin_output",
                            "index0": null
                        }
                    }
                ],
                "siacoinoutputs": [
                    {
                        "value": "49585429860400566009593856",
                        "unlockhash": "c1515352cff287dfab08acff22d82277870e38fdd726d230e602858db92f045bd340ed6803b3",
                        "id": "518c975ebfdb21a6e93e30534454e63e75620dd4eb25a6c78cb4a6b0e04a7f5c",
                        "spent": {
                            "block": "000000000000003ffb1d5162460d2e5bdf64d30fb57d18aceca841d9f4e15065",
                            "blocki": 120064,
                            "tx": "af87a97545d926034a284d84aeadfef8abdb2e1499ef6c2bd3ae071f50e67c9b",
                            "index": 1,
                            "index0": null
                        }
                    },
                    {
                        "value": "10095645765620932018321227776",
                        "unlockhash": "9273a1248920c7785b26f720f285bb9a356c527e20ecf1af747149dc4e91b6326e173219379d",
                        "id": "060bf09cfa4964956709ab3a483e6585bb477d143ad3eb8a64aad1dc6d1bd696",
                        "spent": {
                            "block": "000000000000003ffb1d5162460d2e5bdf64d30fb57d18aceca841d9f4e15065",
                            "blocki": 120064,
                            "tx": "c9931c8263c63634720e78de0c537fe4b08585c4e33cfbdcef5ddbf26ff7e004",
                            "index": 0,
                            "index0": null
                        }
                    }
                ],
                "filecontracts": null,
                "filecontractrevisions": null,
                "storageproofs": null,
                "siafundinputs": null,
                "siafundoutputs": null,
                "minerfees": [],
                "arbitrarydata": [],
                "transactionsignatures": [
                    {
                        "parentid": "72db03dd7dd65161dec1531004efc5f048c34d7feb8313a2f3bae5338372d3f1",
                        "publickeyindex": 0,
                        "timelock": 0,
                        "coveredfields": {
                            "wholetransaction": true,
                            "siacoininputs": [],
                            "siacoinoutputs": [],
                            "filecontracts": [],
                            "filecontractrevisions": [],
                            "storageproofs": [],
                            "siafundinputs": [],
                            "siafundoutputs": [],
                            "minerfees": [],
                            "arbitrarydata": [],
                            "transactionsignatures": []
                        },
                        "signature": "YeEGGgyasfpcwKEpF+q45oKWN8s4//ai+kPUm1s2tyRvKqJHPq/cNNSf9A3xiDIAoecuOumQZRE+i0QXo5/lBQ=="
                    }
                ]
            }
        }
    ],
    "siafund_history": null,
    "next": "",
    "siacoin_history_len": 1,
    "siafund_history_len": 0
}
