{
    "unlockhash": "c7e81145344a0d744f31a069ee58d8ba673570a0d092c74816df2d9bbcb80100d00619a32538",
    "siacoin_history": [
        {
            "income": {
                "value": "2095750000000000000000000000",
                "unlockhash": "c7e81145344a0d744f31a069ee58d8ba673570a0d092c74816df2d9bbcb80100d00619a32538",
                "id": "4fe21e59ad32b05f4cb56ba47e5aa2167c967ad7c57aa2e7081ad4b484dfbd03",
                "spent": {
                    "block": "0000000000000028270d2bbcace7204381c7afb7d855835d559d58f3c422ea7a",
                    "blocki": 109853,
                    "tx": "d1f83ec63fc23d724261f32080aa3c4f8e0c0dee2fd372a454c7cfaf03c32816",
                    "index": 0,
                    "index0": null
                }
            },
            "income_source": {
                "block": "0000000000000028270d2bbcace7204381c7afb7d855835d559d58f3c422ea7a",
                "blocki": 109853,
                "tx": "91213e2bf5a36741599d6fe99c6b8fe6e5a278222d84b36c2e01315d4b72eabd",
                "index": 0,
                "nature": "siacoin_output",
                "index0": null
            },
            "income_tx": {
                "id": "91213e2bf5a36741599d6fe99c6b8fe6e5a278222d84b36c2e01315d4b72eabd",
                "block": "0000000000000028270d2bbcace7204381c7afb7d855835d559d58f3c422ea7a",
                "blocki": 109853,
                "size": 498,
                "siacoininputs": [
                    {
                        "parentid": "ccca75aa1585d615a42a2fa70957e7cd814b83a115b8312495b525dc7a9db217",
                        "unlockconditions": {
                            "timelock": 0,
                            "publickeys": [
                                {
                                    "algorithm": "ed25519",
                                    "key": "53sc+CXSKMOp66aiooQcuUY+6xKKbcrzP62b1rQvUZM="
                                }
                            ],
                            "signaturesrequired": 1
                        },
                        "parent": {
                            "value": "5304927390600000000000000000000",
                            "unlockhash": "68ba0f0a66ad1e7f79a3df5c92e3afc5c62ced5863c364311a912e1fc27e9078fdd820387467"
                        },
                        "source": {
                            "block": "0000000000000028270d2bbcace7204381c7afb7d855835d559d58f3c422ea7a",
                            "blocki": 109853,
                            "tx": "ae1b88468b802474ab7ba237c39bb4e0f97843f0f61ac77727f697c937042cfa",
                            "index": 1,
                            "nature": "siacoin_output",
                            "index0": null
                        }
                    }
                ],
                "siacoinoutputs": [
                    {
                        "value": "2095750000000000000000000000",
                        "unlockhash": "c7e81145344a0d744f31a069ee58d8ba673570a0d092c74816df2d9bbcb80100d00619a32538",
                        "id": "4fe21e59ad32b05f4cb56ba47e5aa2167c967ad7c57aa2e7081ad4b484dfbd03",
                        "spent": {
                            "block": "0000000000000028270d2bbcace7204381c7afb7d855835d559d58f3c422ea7a",
                            "blocki": 109853,
                            "tx": "d1f83ec63fc23d724261f32080aa3c4f8e0c0dee2fd372a454c7cfaf03c32816",
                            "index": 0,
                            "index0": null
                        }
                    },
                    {
                        "value": "5302831640600000000000000000000",
                        "unlockhash": "0f820ff9feb9b23bfcf9f2bfcd6d65a5387fc4de0152059061a8a82b16a43405255fc0681966",
                        "id": "e0af8b7078da629f2ce0db4599ccd1014dd3e7a185210db1e16acb12809eddec",
                        "spent": {
                            "block": "0000000000000028270d2bbcace7204381c7afb7d855835d559d58f3c422ea7a",
                            "blocki": 109853,
                            "tx": "3f9446afe073b4efb5d5417c385d54edb1a293fa7c33eecb9b1501f5084802be",
                            "index": 0,
                            "index0": null
                        }
                    }
                ],
                "filecontracts": null,
                "filecontractrevisions": null,
                "storageproofs": null,
                "siafundinputs": null,
                "siafundoutputs": null,
                "minerfees": [],
                "arbitrarydata": [],
                "transactionsignatures": [
                    {
                        "parentid": "ccca75aa1585d615a42a2fa70957e7cd814b83a115b8312495b525dc7a9db217",
                        "publickeyindex": 0,
                        "timelock": 0,
                        "coveredfields": {
                            "wholetransaction": true,
                            "siacoininputs": [],
                            "siacoinoutputs": [],
                            "filecontracts": [],
                            "filecontractrevisions": [],
                            "storageproofs": [],
                            "siafundinputs": [],
                            "siafundoutputs": [],
                            "minerfees": [],
                            "arbitrarydata": [],
                            "transactionsignatures": []
                        },
                        "signature": "b4TPljQz6z47aJeECydTcaQ12T57Szs96veuDCOcYpVW4DBvHxSkJiTMRtOXlh1TQcgmLdkV5FYllJmlhjtQAw=="
                    }
                ]
            },
            "spent_tx": {
                "id": "d1f83ec63fc23d724261f32080aa3c4f8e0c0dee2fd372a454c7cfaf03c32816",
                "block": "0000000000000028270d2bbcace7204381c7afb7d855835d559d58f3c422ea7a",
                "blocki": 109853,
                "size": 463,
                "siacoininputs": [
                    {
                        "parentid": "4fe21e59ad32b05f4cb56ba47e5aa2167c967ad7c57aa2e7081ad4b484dfbd03",
                        "unlockconditions": {
                            "timelock": 0,
                            "publickeys": [
                                {
                                    "algorithm": "ed25519",
                                    "key": "wSExS/WZqUGHkG8fBjdt6x7Ww/NRcxHkR6U5c5eUbao="
                                }
                            ],
                            "signaturesrequired": 1
                        },
                        "parent": {
                            "value": "2095750000000000000000000000",
                            "unlockhash": "c7e81145344a0d744f31a069ee58d8ba673570a0d092c74816df2d9bbcb80100d00619a32538"
                        },
                        "source": {
                            "block": "0000000000000028270d2bbcace7204381c7afb7d855835d559d58f3c422ea7a",
                            "blocki": 109853,
                            "tx": "91213e2bf5a36741599d6fe99c6b8fe6e5a278222d84b36c2e01315d4b72eabd",
                            "index": 0,
                            "nature": "siacoin_output",
                            "index0": null
                        }
                    }
                ],
                "siacoinoutputs": [
                    {
                        "value": "2095000000000000000000000000",
                        "unlockhash": "90c0c3f974e73922e041b2a2f8badec59ad09fe1f7d1b498e5cb33a0f86b2e25333bc51075b9",
                        "id": "736f5e1d245db2f49481336f9b7c1b31d47347b9fc2f42469a052b4fb77808af",
                        "spent": {
                            "block": "000000000000000725c0cf998063d544040edfba1d9052b1bc5e20d2478a0b75",
                            "blocki": 114449,
                            "tx": "bc3e4186c69c04a9f39d347c2085234de4d7f3ca23f6361345d9696d01d64860",
                            "index": 31,
                            "index0": null
                        }
                    }
                ],
                "filecontracts": null,
                "filecontractrevisions": null,
                "storageproofs": null,
                "siafundinputs": null,
                "siafundoutputs": null,
                "minerfees": [
                    "750000000000000000000000"
                ],
                "arbitrarydata": [],
                "transactionsignatures": [
                    {
                        "parentid": "4fe21e59ad32b05f4cb56ba47e5aa2167c967ad7c57aa2e7081ad4b484dfbd03",
                        "publickeyindex": 0,
                        "timelock": 0,
                        "coveredfields": {
                            "wholetransaction": true,
                            "siacoininputs": [],
                            "siacoinoutputs": [],
                            "filecontracts": [],
                            "filecontractrevisions": [],
                            "storageproofs": [],
                            "siafundinputs": [],
                            "siafundoutputs": [],
                            "minerfees": [],
                            "arbitrarydata": [],
                            "transactionsignatures": []
                        },
                        "signature": "lVn19MpXxAVdi8RAz0rMs1G3NuKHLjsOinftXbnVkFbwwRPxLM8N2Il4An2qsTWJEEmqokRDJlJFQf7Epht/Aw=="
                    }
                ]
            }
        }
    ],
    "siafund_history": null,
    "next": "",
    "siacoin_history_len": 1,
    "siafund_history_len": 0
}
