{
    "id": "6b5cf80822041ecab7331b3b02ac69c7a97fd7ed9e7e1987e53d5bc6e1a1ea23",
    "block": "00000000000002a92926eeef86cd30718100d73078002e56b215e773fbac45f5",
    "blocki": 74517,
    "size": 464,
    "siacoininputs": [
        {
            "parentid": "39faebf7b4e86955bbf7b64ec82522134b4e737f5b0773f6055581e1a7da866a",
            "unlockconditions": {
                "timelock": 0,
                "publickeys": [
                    {
                        "algorithm": "ed25519",
                        "key": "KS1A1sOQarKMKryZPW+Zy/6H3vwsiAC8Ny4nsche8IE="
                    }
                ],
                "signaturesrequired": 1
            },
            "parent": {
                "value": "2184003850043105932000000000",
                "unlockhash": "5144d14d72cc32d9a38a9a196082d6e90a5068b47ed435f64362681aabfe7e0769d12512293c"
            },
            "source": {
                "block": "00000000000002a92926eeef86cd30718100d73078002e56b215e773fbac45f5",
                "blocki": 74517,
                "tx": "1278394ad57d560bd45368c753c743c382c2de4266ee9fddafe9abd8917e749a",
                "index": 0,
                "nature": "siacoin_output",
                "index0": null
            }
        }
    ],
    "siacoinoutputs": [
        {
            "value": "2182003850043105932000000000",
            "unlockhash": "080aea9c34828b7751186098487723cab88ae6dcfdc0ddf9b6c4472018837432edd11c45c098",
            "id": "12b785171f6421a72d8438efb32dce38b4c672cfd6597a63ec30ff706af8fd46",
            "spent": null
        }
    ],
    "filecontracts": null,
    "filecontractrevisions": null,
    "storageproofs": null,
    "siafundinputs": null,
    "siafundoutputs": null,
    "minerfees": [
        "2000000000000000000000000"
    ],
    "arbitrarydata": [],
    "transactionsignatures": [
        {
            "parentid": "39faebf7b4e86955bbf7b64ec82522134b4e737f5b0773f6055581e1a7da866a",
            "publickeyindex": 0,
            "timelock": 0,
            "coveredfields": {
                "wholetransaction": true,
                "siacoininputs": [],
                "siacoinoutputs": [],
                "filecontracts": [],
                "filecontractrevisions": [],
                "storageproofs": [],
                "siafundinputs": [],
                "siafundoutputs": [],
                "minerfees": [],
                "arbitrarydata": [],
                "transactionsignatures": []
            },
            "signature": "Mq3wZIUA5y834647rOyc7MrcK7N7uoGBBmmL5SZvtVyKYE6Z7Qu3Y6JbIpY7YiYy66jmuTXtKP2/q+6ObG2PBg=="
        }
    ]
}
